{
  "id": 10055,
  "año": 2009,
  "tipo": "Resolución",
  "numero": "4121",
  "titulo": "Concejo Deliberante de Zárate",
  "dimension": "General",
  "texto": "Concejo Deliberante de Zárate\nResolución\tNro. 1865.-\nCORRESPONDE A EXPEDIENTE Nº 4121 - H.C.D. 138/09.-\nVISTO:\nLa solicitud de Declaración de Interés Legislativo sobre la realización del 2do. Seminario Regional sobre Responsabilidad Social; y,\nCONSIDERANDO:\nQue, dicho evento es organizado, en conjunto, por el Rotary Club de Zárate y de Campana, entidades estas de bien público de nuestra zona.-\nQue, el tema abordado es de suma importancia para la zona, en lo referente a la responsabilidad social empresarial, dada la gran cantidad de empresas calificadas radicadas en ambos Partidos.-\nPor ello, el\nHONORABLE CONCEJO DELIBERANTE DEL PARTIDO DE\nZARATE\n, \"En el Vigésimo Quinto Aniversario de la Recuperación de la Democracia Argentina\",\nen uso de sus facultades sanciona la siguiente:\nRESOLUCION  Nº 1865.-\nARTÍCULO 1º.-\nEl Honorable Concejo Deliberante del Partido de Zárate declara de Interés Legislativo  la realización del 2do. Seminario Regional sobre Responsabilidad Social a desarrollarse el día 26 de Junio de 2009 en la Ciudad de Campana.-\nARTÍCULO 2º.-\nElévese copia  de la presente Resolución al Rotary Club de Zárate.-\nARTICULO 3º.-\nComuníquese, publíquese, regístrese y archívese. Dada en la Sala de Sesiones del    Honorable  Concejo Deliberante  del Partido  de Zárate, a los cuatro días del mes de Junio de dos mil nueve.-"
}