{
  "id": 10871,
  "año": 2007,
  "tipo": "Ordenanza",
  "numero": "4121",
  "titulo": "Concejo Deliberante de Zárate",
  "dimension": "Hacienda",
  "texto": "Concejo Deliberante de Zárate\nOrdenanza\tNro. 3863\nCORRESPONDE A EXPEDIENTE Nº 4121 – H.C.D. 085/10.-\nV I S T O:\nEl Expediente N°4121-2841/08, y.-\nCONSIDERANDO:\nQue mediante expediente administrativo municipal número 4121-2841/2008, del Departamento Ejecutivo Municipal, se ha reclamado por la firma DESFA S.R.L., el pago de la suma de Pesos Cuatro Mil Setecientos Veinticinco con Cincuenta y Tres Centavos ($4.725,53), en concepto de suministros prestados al Municipio correspondiente al ejercicio fiscal 2007.-\nQue el Departamento de Sistemas confirma la entrega de la mercadería por parte de la Comuna.-\nQue habiéndose recabado los informes y documentación necesaria, el señor Contador Municipal procede a indicar la imputación presupuestaria correspondiente.-\nQue por su parte el Departamento Ejecutivo Municipal, al tomar vista, manifiesta que corresponde reconocer la legitimidad del derecho invocado por el acreedor.-\nQue este Honorable Cuerpo entiende que debe de accederse a lo solicitado a fojas 1, reconociendo la deuda mantenida con la firma DESFA S.R.L., y autorizar al Departamento Ejecutivo Municipal al registro y pago de dicha deuda.-\nPor ello,\nel\nHONORABLE CONCEJO DELIBERANTE DEL\nPARTIDO\nDE ZARATE,\n“En el año del Bicentenario de la Patria”\n,\nen uso de sus facultades sanciona la siguiente:\nO R D E N A N Z A  Nº  3 8 6 3.-\nARTÍCULO 1º.-\nReconózcase la Deuda que este Municipio mantiene con la firma  DESFA S.R.L., C.U.I.T. N°: 30-63234547-6, conforme a la deuda reclamada en el expediente administrativo municipal N° 4121-2841/2008, por el importe de\nPesos Cuatro Mil Setecientos Veinticinco con Cincuenta\ny\nTres Centavos\n($ 4.725,53.-), en los términos el artículo 140º, y concordantes, del Reglamento de Contabilidad y Disposiciones de Administración para las Municipalidades de la Provincia de Buenos Aires y del Decreto Ley 6769/ 58.-\nARTÍCULO 2º.-\nAutorizase al Departamento Ejecutivo Municipal, en los términos  del artículo 140º, y concordantes, del Reglamento de Contabilidad y Disposiciones de Administración para las Municipalidades de la Provincia de Buenos Aires, el registro y pago de la deuda reclamada por la firma DESFA S.R.L., por la suma de\nPesos Cuatro Mil Setecientos Veinticinco con Cincuenta\ny\nTres Centavos\n($ 4.725,53.-) expediente administrativo municipal N° 4121-2841/2008, sobre reconocimiento de deuda por medicamentos e insumos de ejercicios anteriores.-\nARTÍCULO 3º.-\nLas partidas presupuestarias a la que hubiera correspondido ser imputada la erogación reconocida son:\nFinalidad\nPrograma 4 01-01-02 10-00-O O, Útiles, libros, impresiones y encuadernaciones\nDel Presupuesto vigente en el año 2007.-\nARTÍCULO 4º.-\nDése por compensados los excesos presupuestarios que puedan  generarse en las partidas de gastos, informadas en el artículo anterior, como consecuencia del reconocimiento de deuda efectuado en el Artículo Primero de la presente Ordenanza.-\nARTÍCULO 5º.-\nRegístrese en la Contabilidad Municipal el gasto reconocido en el artículo Primero, con Crédito a la cuenta “Deuda Flotante” y con Débito a la cuenta “Resultado de Ejercicios”, para su posterior cancelación.-\nARTÍCULO 6º.-\nComuníquese, Publíquese y Archívese. Dada en la Sala de Sesiones del Honorable Concejo Deliberante del Partido de Zárate, a los seis días del mes de Mayo de dos mil diez.-"
}