{
  "id": 11073,
  "año": 2010,
  "tipo": "Ordenanza",
  "numero": "4121",
  "titulo": "Concejo Deliberante de Zárate",
  "dimension": "Obras Públicas",
  "texto": "Concejo Deliberante de Zárate\nResolución\tNro. 2013\nCORRESPONDE A EXPEDIENTE Nº 4121 - H.C.D. 389/10.-\nVISTO:\nQue este Honorable Concejo Deliberante ha sancionado varias Comunicaciones (Pedidos de informes), dirigidas al Departamento Ejecutivo Municipal, sobre aspectos que hacen al bienestar y calidad de vida de los vecinos del Partido de Zárate; y.-\nCONSIDERANDO:\nQue las Comunicaciones (Pedidos de Informes) constituyen una de las herramientas normativas de este Honorable Concejo Deliberante para atender a los reclamos de los vecinos y las necesidades de sus barrios como, así también, otros aspectos que hacen a la vida diana en nuestra comunidad.-\nQue a la fecha no se ha recibido la información solicitada en las referidas comunicaciones (Pedidos de Informes).-\nQue tal situación dificulta la respuesta que este Honorable Cuerpo debe brindar a los vecinos cuyas necesidades motivaron, en la mayoría de los casos, esas Comunicaciones.-\nPor ello, el\nHONORABLE CONCEJO DELIBERANTE DEL PARTIDO DE ZÁRATE\n, en el\n\"Año del Bicentenario de la Patria\"\nen uso de sus facultades sanciona la siguiente:\nRESOLUCIÓN Nº 2013.-\nARTÍCULO 1°.-\nEl Honorable Concejo Deliberante del Partido de Zárate se dirige al Departamento     Ejecutivo Municipal para que, a la brevedad posible y con el fin de dar respuesta a los problemas y urgencias planteados por los distintos actores sociales del Partido de Zárate, se sirva elevar los requerimientos planteados en las siguientes Comunicaciones (Pedidos de Informes):\nComunicaciones sancionadas en la Segunda Sesión Pública Ordinaria de fecha 8 de abril de 2010.-\n•Comunicación N° 1476 - Expediente HCD N° 098/2010 Solicitando al D.E.M. informe sobre funcionarios que integran el nuevo organigrama municipal.-\n•Comunicación N° 1477 - Expediente HCD N° 099/2010. Solicitando al D.E.M. informe sobre obras en ejecución en la localidad de Lima.-\n•\nComunicación N° 1478 - Expediente HCD N° 100/2010. Solicitando al D.E.M. informe sobre recaudos en seguridad tomados sobre el predio de la ex terminal de Transporte automotor.-\nComunicaciones sancionadas en la Tercera Sesión Pública Ordinaria de fecha 22 de abril de 2010\n•Comunicación N° 1481 - Expediente HCD N° 132/2010. Solicitando al D.E.M. informe sobre basural a cielo abierto existente frente a la calle Maipú, lindando con el Parque de la Cruz.-\n•Comunicación N° 1482 - Expediente HCD N° 136/2010. Solicitando al D.E.M. informe sobre versiones periodísticas que vinculan al Director de Tránsito como supuesto autor de delito penal de lesiones en perjuicio de vecinos.-\nComunicaciones sancionadas en la Cuarta Sesión Pública Ordinaria de fecha 6 de mayo de 2010\n•Comunicación N° 1488 - Expediente HCD N° 158/2010. Solicitando al D.E.M. informe sobre la tala de árboles en calle Andrade al 30 de la ciudad de Zárate.-\nComunicaciones sancionadas en la Quinta Sesión Pública Ordinaria de fecha 20 de mayo de 2010\n•Comunicación N° 1493\n- Expediente HCD N° 193/2010. Solicitando al D.E.M. informe sobre lo actuado según Ordenanza N° 3415/2003 (Expropiación casa Guerci).-\n•Comunicación N° 1494 - Expediente HCD N° 195/2010. Solicitando al D.E.M. informe sobre las tareas de mantenimiento que se realizan en el Palacio Municipal.-\n•Comunicación N° 1496\n- Expediente HCD N° 156/2010. Solicitando al D.E.M. informe sobre la re funcionalización del Tanque de Agua Corriente.-\nARTÍCULO 2°.-\nDése a publicidad en los Medios de Comunicación Social del Partido de Zárate.-\nARTICULO 3º.-\nComuníquese, publíquese, regístrese y archívese. Dada en la Sala de Sesiones  del   Honorable  Concejo Deliberante  del Partido  de Zárate, a los diez días del mes de Agosto de dos mil diez.-"
}