{
  "id": 11105,
  "año": 1968,
  "tipo": "Decreto Concejo",
  "numero": "1129",
  "titulo": "Concejo Deliberante de Zárate",
  "dimension": "Obras Públicas",
  "texto": "Concejo Deliberante de Zárate\nDecreto Concejo\tNro. 1129\nEl Presidente del\nHONORABLE CONCEJO DELIBERANTE\nDEL PARTIDO DE ZARATE\n, en uso de sus facultades sanciona el siguiente:\nDECRETO Nº 1129.-\nARTICULO 1º.-\nDese de baja a partir del día 10 de Diciembre de 2009, en el cargo de Subsecretario del Honorable Concejo Deliberante del Partido de Zárate, al Sr. MARCHIORI Pedro Marcos, D.N.I. Nº 08.189.172, (Legajo Nº 1968) con domicilio en la calle Avda. Anta  Nº 850 de la Ciudad de Zárate.-\nARTICULO 2º.-\nTome conocimiento: Secretaría de Gobierno Municipal, Contaduría,  Oficina de Personal, Oficina de Haberes, dése al Libro de Decretos, Publíquese y Archívese. Dado y firmado por el Sr. Presidente del Honorable Concejo Deliberante del Partido de Zárate en su público despacho a los diez días del mes de Diciembre de dosmil  nueve.-"
}