{
  "id": 11385,
  "año": 1994,
  "tipo": "Ordenanza",
  "numero": "4121",
  "titulo": "Concejo Deliberante de Zárate",
  "dimension": "General",
  "texto": "Concejo Deliberante de Zárate\nOrdenanza\tNro. 2490\nCORRESPONDE A EXPTE. 4121 - HCD 970/87.-\nVISTO:\nEl expediente N° 4121-970/87 presentado por la firma AXOVO S.R.L., solicitando ampliación del Precinto Industrial 7; y.-\nCONSIDERANDO:\nQue el cambio solicitado es a efectos de ampliar el espacio físico en el que desarrolla sus actividades la firma sin incremento de la superficie edificada.-\nQue las instalaciones industriales ocupan el mismo sector del predio originario.-\nQue la misma no implica modificación del rubro o producto elaborado.-\nQue se trata de una industria de productos alimenticios, sin efluentes contaminantes.-\nPor ello, el Honorable Concejo deliberante del Partido de Zárate, en uso de sus facultades, sanciona la siguiente:\nORDENANZA Nº 2490.-\nARTICULO 1º.-\nModificase el Precinto Industrial 7, definido en el artículo 73 de la Ordenanza N° 1994/81, designado catastralmente corno: Circunscripción II, Sección C, Parcela 47h.-\nARTICULO 2°.-\nDenominase Precinto Industrial 7,a la fracción de terreno designada catastralmente como: Circunscripción II, Sección Rural, Parcela 47p, del Partido de Zárate, ubicada en el Área Complementaria, Zona de Uso Agropecuario Intensivo 2, (ZUAI 2).-\nARTICULO 3°.-\nEl Precinto Industrial 7, se destinará a industria de productos alimenticios.-\nARTICULO 4°.-\nEstablecesé para el Precinto Industrial 7, los siguientes indicadores urbanísticos: Volumen Edificatorio: F.O.S.= 0,50.- F.O.T.= 1,00.-\nARTÍCULO 5°.-\nInfraestructura requerida: Además de la existente en la zona, se deberá realizar una zona de protección de cinco metros de ancho en todo el perímetro, la cual será forestada por la industria titular del dominio.-\nARTICULO 6°.-\nTodo pedido de modificación ampliación del tipo de industria instalada en el Precinto Industrial, delimitado \" up-supra\", quedará sujeto al estudio particularizado de la Dirección Municipal de Planeamiento y Desarrollo, según el artículo 76°, de la Ordenanza N° 1994/81.-\nARTICULO 7°.-\nComuníquese, etc. Dada en la Sala de Sesiones del Honorable Concejo Deliberante del Partido de Zárate, a los quince días del mes de Septiembre de mil novecientos ochenta y ocho.-"
}