{
  "id": 12310,
  "año": 2012,
  "tipo": "Ordenanza",
  "numero": "4121",
  "titulo": "Concejo Deliberante de Zárate",
  "dimension": "Obras Públicas",
  "texto": "Concejo Deliberante de Zárate\nOrdenanza\tNro. 4114\nCORRESPONDE A EXPEDIENTE Nº 4121 -H.C.D. 048/13.-\nV I S T O:\nEl expediente Nº 4121-6549/2012, y.-\nCONSIDERANDO:\nQue en el mismo la Secretaría de Obras y Servicios Públicos, se expide respecto de los bienes enumerados que integran el Patrimonio Municipal y que se encuentran en condiciones de ser enajenados en razón del estado de obsolescencia y demás argumentación técnica incorporada al expediente.-\nQue la Ley Orgánica de las Municipalidades establece los procedimientos en el caso de venta y compra de bienes municipales (Art. 54 y siguientes).-\nQue tal situación hace necesario que se proceda a autorizar la venta de los bienes referidos.-\nQue asimismo resulta necesario adecuar el Patrimonio Municipal procediéndose a disponer la baja en el inventario de los referidos bienes una vez producida su enajenación.-\nPor ello,\nel\nHONORABLE CONCEJO DELIBERANTE DEL PARTIDO DE ZARATE\n, en uso de las facultades sanciona la siguiente:\nO R D E N A N Z A  Nº  4 1 1 4.-\nARTÍCULO 1º.-\nAutorízase con arreglo a lo dispuesto por el art.159 del Dto. Ley 6769/58, la enajenación por remate público de los bienes que conforman el patrimonio municipal y que se detallan en el Anexo I de la presente.-\nARTÍCULO 2º.-\nDispónese, una vez perfeccionada la enajenación a la que se refiere el Art. 1º de la presente Ordenanza, la Baja Definitiva de los bienes que integran el Patrimonio Municipal, que obran en planilla anexa y que forman parte del presente como ANEXO I.-\nARTÍCULO 3º.-\nAutorizase a la Contaduría Municipal a que por intermedio del Departamento de Patrimonio identifique y registre la baja de los bienes dispuestos en el artículo precedente, una vez concluido el procedimiento de enajenación por remate público.-\nARTÍCULO 4º.-\nComuníquese, publíquese, regístrese y archívese. Dada en la Sala de Sesiones del Honorable Concejo Deliberante del Partido de Zárate, a los un días del mes de Marzo de dos mil trece.-"
}