{
  "id": 12353,
  "año": 2013,
  "tipo": "Ordenanza",
  "numero": "4121",
  "titulo": "Concejo Deliberante de Zárate",
  "dimension": "Obras Públicas",
  "texto": "Concejo Deliberante de Zárate\nOrdenanza\tNro. 4157\nCORRESPONDE A EXPEDIENTE Nº 4121 -H.C.D. 298/13.-\nV I S T O:\nEl Convenio de Servicios celebrado entre la Municipalidad de Zárate y la V.T.V. NORTE S.A., y.-\nCONSIDERANDO:\nQue, el citado Convenio celebrado entre las partes signatarias, tiene por objeto el Control Técnico del parque automotor de los servicios comunales de transporte denominado servicio de coches remises de la ciudad de Zárate.-\nQue conforme lo dispuesto por el Artículo 410 del Decreto Ley 6.769/58 (Ley Orgánica Municipal) corresponde al Honorable Concejo Deliberante autorizar los Convenios que suscriba el Departamento Ejecutivo.-\nPor ello,\nel HONORABLE CONCEJO DELIBERANTE DEL PARTIDO DE ZARATE,\nen uso de sus facultades sanciona la siguiente:\nO R D E N A N Z A  Nº  4 1 5 7.-\nARTÍCULO 1º.-\nRatificase el CONVENIO DE SERVICIOS celebrado entre la MUNICIPALIDAD DE ZARATE representada por el Señor Intendente Municipal Dn. OSVALDO RAÚL CÁFFARO, y la V.T.V. NORTE S.A. representada por el señor Cdor. MARTIN H. SERRANO el que forma parte de la presente como ANEXO 1.-\nARTÍCULO 2º.-\nComuníquese, publíquese y archívese. Dada en la sala de sesiones del Honorable Concejo Deliberante del Partido de Zárate a los quince días del mes de Agosto de dos mil trece.-\nANEX\nO I\nCONVENIO DE SERVICIOS CON  \"V.T.V. NORTE S.A.\", PARA LA REALIZACION DE CONTROL DE VEHICULOS DE TRANSPORTE DE REMISES DE JURISDICCION COMUNAL LEY 12152.-\nEntre la Municipalidad de Zárate representada en este acto por el Señor Intendente Municipal OSVALDO RAUL CAFFARO, con domicilio en la Ciudad de Zárate, en virtud de la autorización para acceder a los beneficios relacionados con la Ley Nº 12152, Verificación Técnica Vehicular, por una parte y por la otra V.T.V. NORTE S.A., con domicilio en Capitán Bermúdez Nº 4651 Munro Partido de Vicente López, del Servicio de Verificación Técnica Vehicular de la Provincia de Buenos Aires, representado en este acto por el Sr. Cdor. Martin H. Serrano, Titular del Documento Nacional de Identidad Nº 20187565, en su calidad de apoderado, personería acreditada con la documentación obrante se procede a la realización del presente Convenio de Servicios, sujeto a las siguientes clausulas:\nPRIMERA:\nLa Municipalidad de Zárate, dispone de la realización del Control Técnico del parque automotor de los servicios comunales del transporte denominado servicio de coches remises de la ciudad de Zárate.-\nSEGUNDA:\nLa empresa V.T.V. NORTE S.A., realizará los controles impuestos por el artículo 16 de la Ley Nº 13.927 y las Ordenanzas Municipales vigentes, aplicando a los usuarios, comprendido en la Cláusula Primera, un descuento del CINCUENTA POR CIENTO (50%) del cuadro tarifario vigente, cuando dichos servicios sean realizados en las plantas de Verificación Técnica Vehicular (V.T.V.) correspondiente a la zona Nº 1 (Planta Vicente López, Planta San Martin), este descuento se hará efectivo solo aquellos vehículos que realicen la revisión dentro de los plazos de vigencia establecidos.-\nTERCERA:\nLa Municipalidad de Zárate, realizará controles periódicos en la Vía Pública para la fiscalización del cumplimiento de las normas vigentes, de control técnico y habilitación con la participación de inspectores propios y la colaboración del personal de la empresa total y exclusivamente a cargo de esta, para lo que establecerán un cronograma de común acuerdo.-\nCUARTA:\nEl sistema de inspección y control se desarrollara a partir de un mecanismo de turnos, que será prefijado de común acuerdo. La Municipalidad no habilitará vehículos que presten servicio dentro del Partido de Zárate que carezcan de la V.T.V. en vigencia.-\nQUINTA:\nLa Empresa V.T.V. NORTE S.A., enviará a la Dirección de Transporte de Zárate un listado de los vehículos verificados con indicación de la calificación obtenida y la fecha de vencimiento correspondiente, cada vez que sea solicitado, con el fin de facilitar los controles.-\nSEXTA:\nLa vigencia del presente convenio se pauta quedando renovada automáticamente a su vencimiento por periodos anuales si ninguna de las partes manifiesta su voluntad en contrario. Ello sin perjuicio de lo cual, cualquiera de las partes podrá solicitar la resolución anticipada del presente convenio mediante la sola comunicación fehaciente a la contraparte con una anticipación de treinta (30) días, sin que ellos, genere en ningún caso obligación indemnizatoria o resarcitoria entre las mismas. Asimismo las partes, acuerdan que podrán proceder a las modificaciones que pudieran ser necesarias para optimizar el convenio de marras cuando ellas lo estimen convenientes.-\nSEPTIMA:\nLa periodicidad de las verificaciones serán las que imponga el Municipio de Zárate, de acuerdo al uso del vehículo, contemplando como marco las Ordenanzas vigentes y con una frecuencia no inferior a la fijada en el Decreto Provincial Nº 4104/95.-\nOCTAVA:\nPara lograr una mayor comodidad de los clientes de Zárate se trabajara con la modalidad de PREVERIFICACION, lo que permitirá conocer en forma preliminar y antes de abonar la tarifa, las eventuales reparaciones necesarias para aprobar el control técnico.-\nNOVENA:\nDado que el presente se basa en el principio de mutua conveniencia cualquiera de las partes podrá solicitar las modificaciones de una o más clausulas y aun la extinción del presente convenio mediante la sola comunicación fehaciente con una anticipación de treinta días corridos a partir de efectuada la comunicación, sin que ello genere la obligación de indemnizar el lucro cesante.-\nEn prueba de conformidad las partes intervinientes firman tres (3) ejemplares de un mismo tenor y a un solo efecto, en la Ciudad de Zárate a los 5 días del mes de agosto de 2013.-"
}