{
  "id": 12893,
  "año": 2018,
  "tipo": "Ordenanza",
  "numero": "4121",
  "titulo": "Concejo Deliberante de Zárate",
  "dimension": "Obras Públicas",
  "texto": "Concejo Deliberante de Zárate\nOrdenanza\tNro. 4649\nCORRESPONDE A EXPTE. Nº4121 - H.C.D. 211/18.-\nV I S T\nO:\nLo actuado en el Expediente 4121-3422/2018, en el que corren agregadas las actuaciones vinculadas con  la Licitación Pública Nº 17/2018; y.-\nCONSIDERAND\nO:\nQue,  la citada Licitación referida, fue convocada con la finalidad de  seleccionar una empresa destinada para que ejecute la \"OBRA: CORDON CUNETA Y OBRAS COMPLEMENTARIAS - BARRIO PROTIERRA- ETAPA II.-\nQue, al acto de apertura solamente se presento una oferta, correspondiente a la Empresa: CLEANOSOL ARGENTINA S.A.I.C.F.I.-\nQue, en su dictamen de fecha 13/07/18 la Comisión de Preadjudicación, designada por Decreto Municipal Nº 514/18, expresa que \"Considera que la única oferta presentada, es de evidente conveniencia para la Municipalidad\" en atención a lo cual concluye que correspondería adjudicar la licitación a la firma antes mencionada.-\nQue a tal efecto, corresponde la intervención del Honorable Cuerpo Deliberativo, en función de lo dispuesto por el Art.155º de la Ley Orgánica de las Municipalidades.-\nPor ello,\nel HONORABLE CONCEJO DELIBERANTE DEL PARTIDO DE ZÁRATE,\nen uso de sus facultades sanciona la siguiente:\nO R D E N A N Z A  Nº 4 6 4 9.-\nARTÍCULO 1º.-\nAutorícese al Departamento Ejecutivo Municipal, en los términos previstos por el Artículo 155º y concordantes del Decreto-Ley 6.769/58- a adjudicar y contratar la obra objeto de la Licitación Pública Nº 17/18, a la Empresa CLEANOSOL ARGENTINA S.A.I.C.F.I., por un monto de $4.569.549,35 (pesos cuatro millones quinientos sesenta y nueve mil quinientos cuarenta y nueve con treinta y cinco centavos - I.V.A. incluido.-\nARTÍCULO 2°.-\nComuníquese, publíquese, regístrese y archívese. Dado en la Sala de Sesiones del Honorable  Concejo Deliberante  del Partido  de Zárate, a los siete días del mes de Agosto de dos mil dieciocho.-"
}