{
  "id": 13616,
  "año": 2025,
  "tipo": "Ordenanza",
  "numero": "4121",
  "titulo": "Concejo Deliberante de Zárate",
  "dimension": "General",
  "texto": "Concejo Deliberante de Zárate\nOrdenanza\tNro. 5334\nCORRESPONDE A EXPTE. Nº 4121 - H.C.D. 373/25.-\nV I S T O:\nEl expediente Nº 4121-6385/2025; y.-\nCONSIDERAND\nO:\nQue, en las presentes actuaciones tramita el pedido de habilitación municipal, por el señor Alejandro Monti, quien invoca la calidad de apoderado de la firma Flunife S.A., por medio de la cual solicita la habilitación de locales comerciales a nombre de la referida empresa, a quien señala como titular del inmueble descripto catastralmente como Circunscripción: II, Sección: B, Quinta: 20, Parcela: 6, del Partido de Zárate.-\nQue, en tal sentido indica que en el inmueble antes referido se han realizado construcciones con destino a locales comerciales, contando con planos aprobados, y que lo que requiere en concreto es la sanción de una norma de excepción al Código de Planeamiento Urbano del Partido de Zárate, para el desarrollo de actividad comercial en los mismos a través de la explotación por terceros de dichos locales.-\nQue, respecto de la solicitud del dictado de una norma de excepción al Código de Planeamiento del Partido de Zárate, cabe decir que, por imperio de los denominados principios del paralelismo de las formas y paralelismo de las competencias, al ser el citado Código una Ordenanza, las excepciones a la misma, y en ausencia de delegación de facultades, corresponde al propio órgano o poder del Estado municipal que la sancionó.-\nQue, ello importa decir que reposa en cabeza del Honorable Concejo Deliberante del Partido de Zárate la facultad exclusiva y excluyente de dictar normas de excepción al citado cuerpo legal, careciendo el Departamento Ejecutivo Municipal de competencia para el dictado de dicha especie de normas.-\nQue, en orden a que la autorización del rubro generaría mayor actividad económica, lo que podría redundar en generación de empleo, y siendo una actividad que por sus características no generaría inconvenientes en la zona de influencia, y considerando lo aconsejado por las áreas intervinientes, se estima oportuno conferir una habilitación provisoria hasta tanto se sancione una norma de excepción, sujeta al cumplimiento de los requisitos exigidos por la normativa vigente aplicable.-\nQue, en cuanto a las razones que ameritarían contemplar por este Honorable Concejo Deliberante la sanción de la norma de excepción, es oportuno reiterar lo expresado por la Dirección de Comercio, Agro e Islas, que expresa que el inmueble es lindero con el Barrio Los Ceibos y demás urbanizaciones de aledañas, y que el emplazamiento de actividades comerciales minoristas beneficiaría a los vecinos por generar actividades de cercanía y evitar el necesario desplazamiento hacia los centros urbanos con fines comerciales.-\nQue, en ese sentido, es dable destacar que la zona en la que el inmueble se encuentra emplazado corresponde a Residencial Extraurbana (RE), que es una zona destinada a la localización extraurbana de vivienda de intensidad baja, y que admite complementariamente actividades que no requieran una vinculación fluida con el centro urbano.-\nQue, dicha zona -conforme el Cuadro de Usos del Código de Planeamiento- contiene una escasa cantidad de actividades posibles, no admitiendo -en general- aquellas actividades propias de las zonas residenciales de baja o media intensidad, que son los negocios de proximidad, lo que no se condice con el crecimiento actual de la ciudad de Zárate, lo que hace mérito al dictado de una norma de excepción.-\nQue, la Dirección General de Comercio y Transporte y la Subsecretaria de Gobierno recomiendan el dictado de la norma de excepción, siendo opinión de la Asesoría Letrada que ello corresponde al Concejo Deliberante.-\nQue, por lo expuesto es necesario disponer una norma de excepción a la Ordenanza N° 3125, reposando en cabeza de éste Honorable Concejo Deliberante la facultad exclusiva y excluyente de dictar normas de excepción al citado Código de Planeamiento Urbano del Partido de Zárate.-\nQue, con las razones expuestas, y considerando que desde el punto de vista jurídico es factible acceder a lo solicitado, es que se decide por este Honorable Cuerpo, el otorgamiento de una norma de excepción.-\nPor ello, el\nHONORABLE CONCEJO DELIBERANTE DEL PARTIDO DE ZÁRATE\n, en uso de sus facultades sanciona la siguiente:\nORDENANZA Nº 5334.-\nARTÍCULO 1º.-\nExceptuase a la firma FLUNIFE S.A. de lo dispuesto en el Código de Planeamiento Urbano del Partido de Zárate -Ordenanza N° 3125-, en cuanto califica como de \"USO NO PERMITIDO\" para la realización de las actividades descriptas como Comercio Minorista Tipo I y Comercio Minorista Tipo II del Cuadro de Usos del Código, en el inmueble descripto catastralmente como Circunscripción: II, Sección: B, Quinta: 20, Parcela 6, del Partido de Zárate.-\nARTÍCULO 2º.-\nLa excepción que se confiere es de carácter precario, y podrá ser revocada inaudita parte de verificarse incumplimientos graves y retirados a las normas municipales que rigen las actividades comerciales.-\nARTÍCULO 31.-\nComuníquese, publíquese, regístrese y archívese. Dada en la Sala de Sesiones del Honorable Concejo Deliberante del Partido de Zárate, a los diecinueve días del mes de Diciembre de dos mil veinticinco.-\nDRA. YANINA PETRUCCI\nSecretaria del H.C.D.\ndel Partido de Zárate\nDr. Leandro A. Matilla\nPresidente del H.C.D.\ndel Partido de Zárate"
}