{
  "id": 8281,
  "año": 1997,
  "tipo": "Resolución",
  "numero": "4121",
  "titulo": "Concejo Deliberante de Zárate",
  "dimension": "Salud",
  "texto": "Concejo Deliberante de Zárate\nResolución\tNro. 1125\nCORRESPONDE A EXPTE. Nº4121- HCD. 161/01.-\nVISTO:\nQue el 07 de Mayo partió desde La Quiaca - Provincia de Jujuy - la Marcha por la Vida integrada por 300 chicos de 8 a 14 años y organizada por el Movimiento Nacional de los Chicos del Pueblo adherido a la C. T. A. (Central de Trabajadores Argentinos).-\nQue el objetivo es reivindicar los derechos infantiles y pedir el cumplimiento de la Convención de los Derechos del Niño, consagrados en la Constitución Argentina.-\nQue el recorrido de dicha Marcha dura 15 días, transitando más de 2.000 kilómetros y las Provincias de Jujuy, Salta, Tucumán, Santiago del Estero, Córdoba, Santa Fé y Buenos Aires, para arribar el día Martes 22 de Mayo a la Ciudad de Buenos Aires, en cuya histórica Plaza de Mayo se realizará la recepción a los participantes de la Marcha por la Vida.-\nQue dicha Marcha, está encabezada por un trencito que simboliza el Derecho al Jue-go, un Micro - Escuela que refleja el derecho a la Educación, donde maestros dan clases todos los días para no perder la regularidad, un Micro - Hospital, que representa el Derecho a la Salud, que al menos garantizan a todos los chicos de la caravana, como así en cada parada, improvisan ollas populares para simbolizar el Derecho a la Alimentación.-\nQue el Movimiento de los Chicos del Pueblo, realizó entre otras actividades, las si-guientes: en 1995: un Encuentro Nacional de Educadores Populares, en 1997, una Bicicleteada, y en el año 2.000 una Marcha que unió Rosario con Buenos Aires.-\nQue esta Marcha por la Vida, cuenta con la adhesión de personalidades destacadas y apreciadas como lo son: Adolfo Pérez Esquivel, Ernesto Sábato, Joan Manuel Serrat, Osvaldo Bayer, Martha Pelloni, Teresa Parodi, León Gieco, entre otros, como así el apoyo de la C. T. A. y la Funda-ción Pelota de Trapo.-\nQue este Honorable Concejo Deliberante ha realizado en más de una oportunidad, su apoyo y adhesión a las iniciativas llevada adelante por el Movimiento Nacional de los Chicos del Pueblo; y,\nCONSIDERANDO:\nQue una de las acciones de este Cuerpo Legislativo ha sido acompañar y pro-mover toda actividad que entre otras, reivindique los Derechos Humanos en toda su dimensión y amplitud, como resultan ser los Derechos de los Niños.-\nPor ello, el HONORABLE CONCEJO DELIBERANTE DEL PARTIDO DE ZARATE, en uso de sus facultades sanciona la siguiente:\nR E S O L U C I O N  Nº 1 1 2 5.-\nARTICULO 1º.- El Honorable Concejo Deliberante de Zárate expresa su adhesión a la Marcha por la ---------------------  Vida que realiza el Movimiento Nacional de los Chicos del Pueblo - adherido a la C. T. A. - que se inició el 07 de Mayo desde La Quiaca (Prov. de Jujuy) y que finalizará el 22 de Mayo, arribando a la Ciudad Autónoma de Buenos Aires en un acto a efectuarse en la histórica Plaza de Mayo.----------------------------------------------------------------------------------------------------------------------------------\nARTICULO 2º.- El Honorable Concejo Deliberante de Zárate resuelve enviar copia de la presente Re- ---------------------  solución a: Movimiento Nacional de los Chicos del Pueblo (C. T. A. Nacional), a la C. T. A. Regional Zárate - Campana y al Gobierno Nacional.------------------------------------------------------------\nARTICULO 3.- Comuníquese, publíquese y archívese. Dada en la Sala de Sesiones del Honorable    --------------------  Concejo Deliberante del Partido de Zárate, a los diecisiete días del mes de Mayo del dosmil uno.--------------------------------------------------------------------------------------------------------------------------"
}